deepseek_tokenizer-0.1.3.dist-info/METADATA
deepseek_tokenizer-0.1.3.dist-info/WHEEL
deepseek_tokenizer-0.1.3.dist-info/entry_points.txt
deepseek_tokenizer/__init__.py
deepseek_tokenizer/tokenizer.json
deepseek_tokenizer/tokenizer_config.json
deepseek_tokenizer-0.1.3.dist-info/RECORD
