Metadata-Version: 2.1
Name: deepseek-tokenizer
Version: 0.1.3
Summary: Lightweight tokenizer for deepseek
Author-Email: Anderson <andersonby@163.com>
License: MIT
Project-URL: Homepage, https://github.com/AndersonBY/deepseek-tokenizer
Requires-Python: >=3.8
Requires-Dist: tokenizers>=0.20.0
